autoform_mcp.py
autoform_mcp-0.1.8.dist-info/licenses/LICENSE
autoform_mcp-0.1.8.dist-info/METADATA
autoform_mcp-0.1.8.dist-info/WHEEL
autoform_mcp-0.1.8.dist-info/entry_points.txt
autoform_mcp-0.1.8.dist-info/top_level.txt
autoform_mcp-0.1.8.dist-info/RECORD
