Metadata-Version: 2.4
Name: autoform-mcp
Version: 0.1.8
Summary: MCP server for the Autoform API from Slovensko.Digital
Requires-Python: >=3.12
License-File: LICENSE
Requires-Dist: fastmcp>=2.14.0
Requires-Dist: httpx>=0.28.0
Provides-Extra: dev
Requires-Dist: pytest>=8.0.0; extra == "dev"
Requires-Dist: pytest-asyncio>=0.24.0; extra == "dev"
Dynamic: license-file
